flexmod/__init__.py
flexmod-0.1.2.dist-info/LICENSE
flexmod-0.1.2.dist-info/METADATA
flexmod-0.1.2.dist-info/WHEEL
flexmod-0.1.2.dist-info/top_level.txt
flexmod-0.1.2.dist-info/RECORD
